_tmdsclient_version.py
tmdsclient/__init__.py
tmdsclient/py.typed
tmdsclient/client/__init__.py
tmdsclient/client/config.py
tmdsclient/client/oauth.py
tmdsclient/client/tmdsclient.py
tmdsclient/models/__init__.py
tmdsclient/models/adresse.py
tmdsclient/models/anschlussobjekt.py
tmdsclient/models/bo4e_stub.py
tmdsclient/models/jsonpatch.py
tmdsclient/models/marktlokation.py
tmdsclient/models/messlokation.py
tmdsclient/models/netzvertrag.py
tmdsclient/models/partneradresse.py
tmdsclient/models/patches.py
tmdsclient/models/utils.py
tmdsclient/models/zaehler.py
tmdsclient/models/zaehler_bo_model.py
tmdsclient/models/zaehlergroesse.py
tmdsclient/models/zaehlerhersteller.py
tmdsclient/models/zaehlwerk.py
tmdsclient/models/zeitscheibe.py
tmdsclient-0.7.0.dist-info/METADATA
tmdsclient-0.7.0.dist-info/WHEEL
tmdsclient-0.7.0.dist-info/licenses/LICENSE
tmdsclient-0.7.0.dist-info/RECORD
