Metadata-Version: 2.4
Name: tmdsclient
Version: 0.7.0
Summary: Fully typed, async client library for Technical Master Data Service (TMDS)
Project-URL: Changelog, https://github.com/Hochfrequenz/tmdsclient.py/releases
Project-URL: Homepage, https://github.com/Hochfrequenz/tmdsclient.py
Author-email: Hochfreuqenz Unternehmensberatung GmbH <info+github@hochfrequenz.de>
License: MIT
License-File: LICENSE
Keywords: technical master data,tmds
Classifier: Development Status :: 4 - Beta
Classifier: Environment :: Console
Classifier: Intended Audience :: Developers
Classifier: License :: OSI Approved :: MIT License
Classifier: Operating System :: OS Independent
Classifier: Programming Language :: Python
Classifier: Programming Language :: Python :: 3 :: Only
Classifier: Programming Language :: Python :: 3.11
Classifier: Programming Language :: Python :: 3.12
Classifier: Programming Language :: Python :: 3.13
Requires-Python: >=3.11
Requires-Dist: aioauth-client
Requires-Dist: aiohttp[speedups]>=3.9.10
Requires-Dist: bo4e>=202401.1.1
Requires-Dist: jsonpatch
Requires-Dist: more-itertools
Requires-Dist: pydantic>=2.0.0
Requires-Dist: pyjwt
Provides-Extra: coverage
Requires-Dist: coverage==7.6.12; extra == 'coverage'
Provides-Extra: formatting
Requires-Dist: black==25.1.0; extra == 'formatting'
Requires-Dist: isort==6.0.1; extra == 'formatting'
Provides-Extra: linting
Requires-Dist: pylint-pydantic==0.3.5; extra == 'linting'
Requires-Dist: pylint==3.3.4; extra == 'linting'
Provides-Extra: packaging
Requires-Dist: build==1.2.2.post1; extra == 'packaging'
Requires-Dist: twine==6.1.0; extra == 'packaging'
Provides-Extra: spellcheck
Requires-Dist: codespell==2.4.1; extra == 'spellcheck'
Provides-Extra: tests
Requires-Dist: aioresponses==0.7.8; extra == 'tests'
Requires-Dist: pytest-asyncio==0.25.3; extra == 'tests'
Requires-Dist: pytest==8.3.5; extra == 'tests'
Provides-Extra: type-check
Requires-Dist: mypy[pydantic]==1.15.0; extra == 'type-check'
Requires-Dist: types-pytz==2025.1.0.20250204; extra == 'type-check'
